{"board":{"cells":[{"confirmed":true,"guess":"S","timestamp":196736},{"confirmed":true,"guess":"H","timestamp":196736},{"confirmed":true,"guess":"O","timestamp":196736},{"confirmed":true,"guess":"N","timestamp":196736},{"confirmed":true,"guess":"D","timestamp":196736},{"confirmed":true,"guess":"A","timestamp":196736},{"blank":true},{"confirmed":true,"guess":"C","timestamp":196736},{"confirmed":true,"guess":"H","timestamp":196736},{"confirmed":true,"guess":"E","timestamp":196736},{"confirmed":true,"guess":"A","timestamp":196736},{"confirmed":true,"guess":"T","timestamp":196736},{"confirmed":true,"guess":"D","timestamp":196736},{"confirmed":true,"guess":"A","timestamp":196736},{"confirmed":true,"guess":"Y","timestamp":196736},{"confirmed":true,"guess":"T","timestamp":196736},{"confirmed":true,"guess":"O","timestamp":196736},{"confirmed":true,"guess":"P","timestamp":196736},{"confirmed":true,"guess":"O","timestamp":196736},{"confirmed":true,"guess":"U","timestamp":196736},{"confirmed":true,"guess":"T","timestamp":196736},{"blank":true},{"confirmed":true,"guess":"R","timestamp":196736},{"confirmed":true,"guess":"O","timestamp":196736},{"confirmed":true,"guess":"G","timestamp":196736},{"confirmed":true,"guess":"U","timestamp":196736},{"confirmed":true,"guess":"E","timestamp":196736},{"confirmed":true,"guess":"O","timestamp":196736},{"confirmed":true,"guess":"N","timestamp":196736},{"confirmed":true,"guess":"E","timestamp":196736},{"confirmed":true,"guess":"A","timestamp":196736},{"confirmed":true,"guess":"M","timestamp":196736},{"confirmed":true,"guess":"E","timestamp":196736},{"confirmed":true,"guess":"N","timestamp":196736},{"confirmed":true,"guess":"D","timestamp":196736},{"confirmed":true,"guess":"S","timestamp":196736},{"blank":true},{"confirmed":true,"guess":"A","timestamp":196736},{"confirmed":true,"guess":"L","timestamp":196736},{"confirmed":true,"guess":"A","timestamp":196736},{"confirmed":true,"guess":"N","timestamp":196736},{"confirmed":true,"guess":"A","timestamp":196736},{"confirmed":true,"guess":"L","timestamp":196736},{"confirmed":true,"guess":"D","timestamp":196736},{"confirmed":true,"guess":"A","timestamp":196736},{"confirmed":true,"guess":"R","timestamp":196736},{"confirmed":true,"guess":"E","timestamp":196736},{"confirmed":true,"guess":"D","timestamp":196736},{"confirmed":true,"guess":"O","timestamp":196736},{"confirmed":true,"guess":"S","timestamp":196736},{"confirmed":true,"guess":"E","timestamp":196736},{"blank":true},{"confirmed":true,"guess":"W","timestamp":196736},{"confirmed":true,"guess":"E","timestamp":196736},{"confirmed":true,"guess":"N","timestamp":196736},{"confirmed":true,"guess":"T","timestamp":196736},{"confirmed":true,"guess":"T","timestamp":196736},{"confirmed":true,"guess":"O","timestamp":196736},{"confirmed":true,"guess":"I","timestamp":196736},{"confirmed":true,"guess":"T","timestamp":196736},{"confirmed":true,"guess":"G","timestamp":196736},{"confirmed":true,"guess":"A","timestamp":196736},{"confirmed":true,"guess":"P","timestamp":196736},{"confirmed":true,"guess":"S","timestamp":196736},{"blank":true},{"confirmed":true,"guess":"A","timestamp":196736},{"confirmed":true,"guess":"C","timestamp":196736},{"confirmed":true,"guess":"L","timestamp":196736},{"confirmed":true,"guess":"U","timestamp":196736},{"blank":true},{"blank":true},{"confirmed":true,"guess":"A","timestamp":196736},{"confirmed":true,"guess":"R","timestamp":196736},{"confirmed":true,"guess":"E","timestamp":196736},{"confirmed":true,"guess":"S","timestamp":196736},{"confirmed":true,"guess":"A","timestamp":196736},{"confirmed":true,"guess":"L","timestamp":196736},{"confirmed":true,"guess":"I","timestamp":196736},{"blank":true},{"blank":true},{"blank":true},{"confirmed":true,"guess":"P","timestamp":196736},{"confirmed":true,"guess":"I","timestamp":196736},{"confirmed":true,"guess":"P","timestamp":196736},{"confirmed":true,"guess":"E","timestamp":196736},{"timestamp":80493},{"confirmed":true,"guess":"S","timestamp":196736},{"blank":true},{"blank":true},{"blank":true},{"confirmed":true,"guess":"Z","timestamp":196736},{"confirmed":true,"guess":"O","timestamp":196736},{"confirmed":true,"guess":"E","timestamp":196736},{"confirmed":true,"guess":"K","timestamp":196736},{"confirmed":true,"guess":"A","timestamp":196736},{"confirmed":true,"guess":"Z","timestamp":196736},{"confirmed":true,"guess":"A","timestamp":196736},{"confirmed":true,"guess":"N","timestamp":196736},{"blank":true},{"confirmed":true,"guess":"N","timestamp":196736},{"timestamp":63402},{"confirmed":true,"guess":"T","timestamp":196736},{"timestamp":63397},{"timestamp":80992},{"timestamp":63396},{"confirmed":true,"guess":"E","timestamp":196736},{"confirmed":true,"guess":"N","timestamp":196736},{"confirmed":true,"guess":"C","timestamp":196736},{"confirmed":true,"guess":"A","timestamp":196736},{"confirmed":true,"guess":"S","timestamp":196736},{"confirmed":true,"guess":"E","timestamp":196736},{"confirmed":true,"guess":"S","timestamp":196736},{"blank":true},{"timestamp":80449},{"confirmed":true,"guess":"O","timestamp":196736},{},{"confirmed":true,"guess":"E","timestamp":196736},{"timestamp":29855},{"timestamp":80992},{"timestamp":63401},{"confirmed":true,"guess":"S","timestamp":196736},{"confirmed":true,"guess":"E","timestamp":196736},{"confirmed":true,"guess":"E","timestamp":196736},{"confirmed":true,"guess":"T","timestamp":196736},{"confirmed":true,"guess":"H","timestamp":196736},{"confirmed":true,"guess":"E","timestamp":196736},{"blank":true},{},{"timestamp":80448},{"confirmed":true,"guess":"S","timestamp":196736},{},{"confirmed":true,"guess":"R","timestamp":196736},{"timestamp":29855},{},{"confirmed":true,"guess":"S","timestamp":196736},{"blank":true},{"blank":true},{"blank":true},{"confirmed":true,"guess":"Y","timestamp":196736},{"confirmed":true,"guess":"E","timestamp":196736},{"confirmed":true,"guess":"S","timestamp":196736},{"confirmed":true,"guess":"A","timestamp":196736},{"confirmed":true,"guess":"N","timestamp":196736},{"confirmed":true,"guess":"D","timestamp":196736},{"blank":true},{"blank":true},{"blank":true},{"timestamp":80983},{"timestamp":80983},{"timestamp":80983},{"confirmed":true,"guess":"C","timestamp":196736},{"confirmed":true,"guess":"R","timestamp":196736},{"confirmed":true,"guess":"O","timestamp":196736},{"confirmed":true,"guess":"P","timestamp":196736},{"blank":true},{"blank":true},{"confirmed":true,"guess":"D","timestamp":196736},{"confirmed":true,"guess":"E","timestamp":196736},{"confirmed":true,"guess":"E","timestamp":196736},{"confirmed":true,"guess":"P","timestamp":196736},{"blank":true},{"timestamp":80996},{"timestamp":29855},{},{},{"confirmed":true,"guess":"L","timestamp":196736},{"confirmed":true,"guess":"I","timestamp":196736},{"confirmed":true,"guess":"M","timestamp":196736},{"confirmed":true,"guess":"E","timestamp":196736},{"confirmed":true,"guess":"A","timestamp":196736},{"confirmed":true,"guess":"D","timestamp":196736},{"confirmed":true,"guess":"E","timestamp":196736},{"confirmed":true,"guess":"S","timestamp":196736},{"blank":true},{},{"confirmed":true,"guess":"S","timestamp":196736},{"timestamp":80996},{"timestamp":29853},{},{},{"confirmed":true,"guess":"O","timestamp":196736},{"confirmed":true,"guess":"V","timestamp":196736},{"confirmed":true,"guess":"E","timestamp":196736},{"confirmed":true,"guess":"R","timestamp":196736},{"confirmed":true,"guess":"L","timestamp":196736},{"confirmed":true,"guess":"A","timestamp":196736},{"confirmed":true,"guess":"P","timestamp":196736},{"confirmed":true,"guess":"S","timestamp":196736},{"blank":true},{},{"confirmed":true,"guess":"U","timestamp":196736},{"timestamp":80996},{"timestamp":29853},{},{},{"confirmed":true,"guess":"M","timestamp":196736},{"confirmed":true,"guess":"A","timestamp":196736},{"confirmed":true,"guess":"G","timestamp":196736},{"confirmed":true,"guess":"R","timestamp":196736},{"confirmed":true,"guess":"I","timestamp":196736},{"confirmed":true,"guess":"T","timestamp":196736},{"confirmed":true,"guess":"T","timestamp":196736},{"confirmed":true,"guess":"E","timestamp":196736},{"blank":true},{},{"confirmed":true,"guess":"P","timestamp":196736},{"timestamp":81006},{"timestamp":29853},{},{},{"confirmed":true,"guess":"P","timestamp":196736},{"confirmed":true,"guess":"L","timestamp":196736},{"confirmed":true,"guess":"A","timestamp":196736},{"confirmed":true,"guess":"Y","timestamp":196736},{"confirmed":true,"guess":"T","timestamp":196736},{"confirmed":true,"guess":"E","timestamp":196736},{"confirmed":true,"guess":"S","timestamp":196736},{"confirmed":true,"guess":"T","timestamp":196736},{"blank":true},{"confirmed":true,"guess":"S","timestamp":196736},{"confirmed":true,"guess":"E","timestamp":196736},{"confirmed":true,"guess":"X","timestamp":196736},{"confirmed":true,"guess":"T","timestamp":196736},{"confirmed":true,"guess":"E","timestamp":196736},{"confirmed":true,"guess":"T","timestamp":196736}]},"calcs":{"percentFilled":82,"secondsSpentSolving":1486},"firsts":{"opened":1539413502},"lastCommitID":"58AF56","puzzleID":15818,"timestamp":1539610253,"userID":55348624,"minGuessTime":1539413513}