{"board":{"cells":[{"confirmed":true,"guess":"H","timestamp":1546269203},{"confirmed":true,"guess":"O","timestamp":1546269203},{"confirmed":true,"guess":"T","timestamp":1546269203},{"confirmed":true,"guess":"T","timestamp":1546269203},{"confirmed":true,"guess":"U","timestamp":1546269203},{"confirmed":true,"guess":"B","timestamp":1546269203},{"blank":true},{"confirmed":true,"guess":"T","timestamp":1546269203},{"confirmed":true,"guess":"I","timestamp":1546269203},{"confirmed":true,"guess":"M","timestamp":1546269203},{"confirmed":true,"guess":"B","timestamp":1546269203},{"confirmed":true,"guess":"R","timestamp":1546269203},{"confirmed":true,"guess":"E","timestamp":1546269203},{"blank":true},{"blank":true},{"confirmed":true,"guess":"B","timestamp":1546269203},{"confirmed":true,"guess":"I","timestamp":1546269203},{"confirmed":true,"guess":"S","timestamp":1546269203},{"confirmed":true,"guess":"S","timestamp":1546269203},{"confirmed":true,"guess":"A","timestamp":1546269203},{"confirmed":true,"guess":"U","timestamp":1546269203},{"confirmed":true,"guess":"U","timestamp":1546269203},{"confirmed":true,"guess":"N","timestamp":1546269203},{"confirmed":true,"guess":"W","timestamp":1546269203},{"confirmed":true,"guess":"I","timestamp":1546269203},{"confirmed":true,"guess":"S","timestamp":1546269203},{"confirmed":true,"guess":"E","timestamp":1546269203},{"blank":true},{"confirmed":true,"guess":"R","timestamp":1546269203},{"confirmed":true,"guess":"O","timestamp":1546269203},{"confirmed":true,"guess":"A","timestamp":1546269203},{"confirmed":true,"guess":"R","timestamp":1546269203},{"confirmed":true,"guess":"I","timestamp":1546269203},{"confirmed":true,"guess":"N","timestamp":1546269203},{"confirmed":true,"guess":"G","timestamp":1546269203},{"blank":true},{"confirmed":true,"guess":"A","timestamp":1546269203},{"confirmed":true,"guess":"C","timestamp":1546269203},{"confirmed":true,"guess":"C","timestamp":1546269203},{"confirmed":true,"guess":"E","timestamp":1546269203},{"confirmed":true,"guess":"P","timestamp":1546269203},{"confirmed":true,"guess":"T","timestamp":1546269203},{"confirmed":true,"guess":"B","timestamp":1546269203},{"confirmed":true,"guess":"L","timestamp":1546269203},{"confirmed":true,"guess":"I","timestamp":1546269203},{"confirmed":true,"guess":"M","timestamp":1546269203},{"confirmed":true,"guess":"E","timestamp":1546269203},{"confirmed":true,"guess":"Y","timestamp":1546269203},{"blank":true},{"confirmed":true,"guess":"I","timestamp":1546269203},{"confirmed":true,"guess":"N","timestamp":1546269203},{"confirmed":true,"guess":"R","timestamp":1546269203},{"confirmed":true,"guess":"A","timestamp":1546269203},{"confirmed":true,"guess":"N","timestamp":1546269203},{"confirmed":true,"guess":"G","timestamp":1546269203},{"confirmed":true,"guess":"E","timestamp":1546269203},{"blank":true},{"confirmed":true,"guess":"S","timestamp":1546269203},{"confirmed":true,"guess":"E","timestamp":1546269203},{"confirmed":true,"guess":"R","timestamp":1546269203},{"confirmed":true,"guess":"A","timestamp":1546269203},{"confirmed":true,"guess":"P","timestamp":1546269203},{"confirmed":true,"guess":"E","timestamp":1546269203},{"confirmed":true,"guess":"B","timestamp":1546269203},{"confirmed":true,"guess":"I","timestamp":1546269203},{"confirmed":true,"guess":"T","timestamp":1546269203},{"confirmed":true,"guess":"E","timestamp":1546269203},{"blank":true},{"confirmed":true,"guess":"O","timestamp":1546269203},{"confirmed":true,"guess":"R","timestamp":1546269203},{"confirmed":true,"guess":"B","timestamp":1546269203},{"confirmed":true,"guess":"I","timestamp":1546269203},{"confirmed":true,"guess":"T","timestamp":1546269203},{"confirmed":true,"guess":"S","timestamp":1546269203},{"blank":true},{"confirmed":true,"guess":"L","timestamp":1546269203},{"confirmed":true,"guess":"I","timestamp":1546269203},{"confirmed":true,"guess":"B","timestamp":1546269203},{"confirmed":true,"guess":"E","timestamp":1546269203},{"confirmed":true,"guess":"R","timestamp":1546269203},{"confirmed":true,"guess":"A","timestamp":1546269203},{"confirmed":true,"guess":"L","timestamp":1546269203},{"blank":true},{"blank":true},{"confirmed":true,"guess":"U","timestamp":1546269203},{"confirmed":true,"guess":"N","timestamp":1546269203},{"confirmed":true,"guess":"C","timestamp":1546269203},{"blank":true},{"confirmed":true,"guess":"S","timestamp":1546269203},{"confirmed":true,"guess":"N","timestamp":1546269203},{"confirmed":true,"guess":"E","timestamp":1546269203},{"confirmed":true,"guess":"E","timestamp":1546269203},{"confirmed":true,"guess":"Z","timestamp":1546269203},{"checked":true,"guess":"E","modified":true,"timestamp":1546269208},{"blank":true},{"confirmed":true,"guess":"I","timestamp":1546269203},{"confirmed":true,"guess":"E","timestamp":1546269203},{"confirmed":true,"guess":"S","timestamp":1546269203},{"confirmed":true,"guess":"T","timestamp":1546269203},{"blank":true},{"blank":true},{"confirmed":true,"guess":"P","timestamp":1546269203},{"confirmed":true,"guess":"D","timestamp":1546269203},{"confirmed":true,"guess":"T","timestamp":1546269203},{"blank":true},{"confirmed":true,"guess":"B","timestamp":1546269203},{"confirmed":true,"guess":"E","timestamp":1546269203},{"confirmed":true,"guess":"H","timestamp":1546269203},{"confirmed":true,"guess":"I","timestamp":1546269203},{"confirmed":true,"guess":"N","timestamp":1546269203},{"confirmed":true,"guess":"D","timestamp":1546269203},{"confirmed":true,"guess":"S","timestamp":1546269203},{"confirmed":true,"guess":"C","timestamp":1546269203},{"confirmed":true,"guess":"E","timestamp":1546269203},{"confirmed":true,"guess":"N","timestamp":1546269203},{"confirmed":true,"guess":"E","timestamp":1546269203},{"confirmed":true,"guess":"S","timestamp":1546269203},{"blank":true},{"confirmed":true,"guess":"E","timestamp":1546269203},{"confirmed":true,"guess":"W","timestamp":1546269203},{"confirmed":true,"guess":"A","timestamp":1546269203},{"confirmed":true,"guess":"N","timestamp":1546269203},{"blank":true},{"confirmed":true,"guess":"E","timestamp":1546269203},{"confirmed":true,"guess":"A","timestamp":1546269203},{"confirmed":true,"guess":"T","timestamp":1546269203},{"blank":true},{"blank":true},{"blank":true},{"confirmed":true,"guess":"S","timestamp":1546269203},{"confirmed":true,"guess":"E","timestamp":1546269203},{"confirmed":true,"guess":"P","timestamp":1546269203},{"confirmed":true,"guess":"I","timestamp":1546269203},{"confirmed":true,"guess":"A","timestamp":1546269203},{"confirmed":true,"guess":"S","timestamp":1546269203},{"blank":true},{"confirmed":true,"guess":"W","timestamp":1546269203},{"confirmed":true,"guess":"E","timestamp":1546269203},{"confirmed":true,"guess":"L","timestamp":1546269203},{"confirmed":true,"guess":"L","timestamp":1546269203},{"confirmed":true,"guess":"O","timestamp":1546269203},{"confirmed":true,"guess":"F","timestamp":1546269203},{"confirmed":true,"guess":"F","timestamp":1546269203},{"confirmed":true,"guess":"M","timestamp":1546269203},{"confirmed":true,"guess":"A","timestamp":1546269203},{"confirmed":true,"guess":"R","timestamp":1546269203},{"confirmed":true,"guess":"K","timestamp":1546269203},{"confirmed":true,"guess":"J","timestamp":1546269203},{"confirmed":true,"guess":"U","timestamp":1546269203},{"confirmed":true,"guess":"G","timestamp":1546269203},{"confirmed":true,"guess":"H","timestamp":1546269203},{"confirmed":true,"guess":"E","timestamp":1546269203},{"confirmed":true,"guess":"A","timestamp":1546269203},{"confirmed":true,"guess":"D","timestamp":1546269203},{"blank":true},{"blank":true},{"confirmed":true,"guess":"S","timestamp":1546269203},{"confirmed":true,"guess":"E","timestamp":1546269203},{"confirmed":true,"guess":"R","timestamp":1546269203},{"confirmed":true,"guess":"E","timestamp":1546269203},{"blank":true},{"blank":true},{"confirmed":true,"guess":"O","timestamp":1546269203},{"confirmed":true,"guess":"C","timestamp":1546269203},{"confirmed":true,"guess":"E","timestamp":1546269203},{"confirmed":true,"guess":"L","timestamp":1546269203},{"confirmed":true,"guess":"O","timestamp":1546269203},{"confirmed":true,"guess":"T","timestamp":1546269203},{"confirmed":true,"guess":"A","timestamp":1546269203},{"confirmed":true,"guess":"T","timestamp":1546269203},{"confirmed":true,"guess":"I","timestamp":1546269203},{"confirmed":true,"guess":"T","timestamp":1546269203},{"blank":true},{"confirmed":true,"guess":"L","timestamp":1546269203},{"confirmed":true,"guess":"E","timestamp":1546269203},{"confirmed":true,"guess":"A","timestamp":1546269203},{"confirmed":true,"guess":"P","timestamp":1546269203},{"confirmed":true,"guess":"T","timestamp":1546269203},{"blank":true},{"confirmed":true,"guess":"E","timestamp":1546269203},{"confirmed":true,"guess":"A","timestamp":1546269203},{"confirmed":true,"guess":"G","timestamp":1546269203},{"confirmed":true,"guess":"E","timestamp":1546269203},{"confirmed":true,"guess":"R","timestamp":1546269203},{"confirmed":true,"guess":"E","timestamp":1546269203},{"confirmed":true,"guess":"R","timestamp":1546269203},{"blank":true},{"blank":true},{"blank":true},{"confirmed":true,"guess":"F","timestamp":1546269203},{"confirmed":true,"guess":"I","timestamp":1546269203},{"confirmed":true,"guess":"N","timestamp":1546269203},{"confirmed":true,"guess":"A","timestamp":1546269203},{"confirmed":true,"guess":"L","timestamp":1546269203},{"confirmed":true,"guess":"E","timestamp":1546269203},{"blank":true},{"confirmed":true,"guess":"M","timestamp":1546269203},{"confirmed":true,"guess":"E","timestamp":1546269203},{"confirmed":true,"guess":"R","timestamp":1546269203},{"confirmed":true,"guess":"E","timestamp":1546269203},{"blank":true},{"confirmed":true,"guess":"F","timestamp":1546269203},{"confirmed":true,"guess":"O","timestamp":1546269203},{"confirmed":true,"guess":"V","timestamp":1546269203},{"confirmed":true,"guess":"E","timestamp":1546269203},{"confirmed":true,"guess":"A","timestamp":1546269203},{"blank":true},{"confirmed":true,"guess":"V","timestamp":1546269203},{"confirmed":true,"guess":"E","timestamp":1546269203},{"confirmed":true,"guess":"T","timestamp":1546269203},{"confirmed":true,"guess":"A","timestamp":1546269203},{"confirmed":true,"guess":"C","timestamp":1546269203},{"confirmed":true,"guess":"U","timestamp":1546269203},{"confirmed":true,"guess":"R","timestamp":1546269203},{"confirmed":true,"guess":"A","timestamp":1546269203},{"blank":true},{"confirmed":true,"guess":"O","timestamp":1546269203},{"confirmed":true,"guess":"U","timestamp":1546269203},{"confirmed":true,"guess":"T","timestamp":1546269203},{"confirmed":true,"guess":"O","timestamp":1546269203},{"confirmed":true,"guess":"F","timestamp":1546269203},{"confirmed":true,"guess":"B","timestamp":1546269203},{"confirmed":true,"guess":"L","timestamp":1546269203},{"confirmed":true,"guess":"U","timestamp":1546269203},{"confirmed":true,"guess":"E","timestamp":1546269203},{"blank":true},{"confirmed":true,"guess":"S","timestamp":1546269203},{"confirmed":true,"guess":"L","timestamp":1546269203},{"confirmed":true,"guess":"O","timestamp":1546269203},{"confirmed":true,"guess":"T","timestamp":1546269203},{"confirmed":true,"guess":"H","timestamp":1546269203},{"confirmed":true,"guess":"R","timestamp":1546269203},{"confirmed":true,"guess":"A","timestamp":1546269203},{"confirmed":true,"guess":"P","timestamp":1546269203},{"blank":true},{"confirmed":true,"guess":"B","timestamp":1546269203},{"confirmed":true,"guess":"R","timestamp":1546269203},{"confirmed":true,"guess":"E","timestamp":1546269203},{"confirmed":true,"guess":"S","timestamp":1546269203},{"confirmed":true,"guess":"T","timestamp":1546269203},{"blank":true},{"confirmed":true,"guess":"S","timestamp":1546269203},{"confirmed":true,"guess":"U","timestamp":1546269203},{"confirmed":true,"guess":"E","timestamp":1546269203},{"confirmed":true,"guess":"D","timestamp":1546269203},{"blank":true},{"confirmed":true,"guess":"S","timestamp":1546269203},{"confirmed":true,"guess":"T","timestamp":1546269203},{"confirmed":true,"guess":"A","timestamp":1546269203},{"confirmed":true,"guess":"C","timestamp":1546269203},{"confirmed":true,"guess":"H","timestamp":1546269203},{"confirmed":true,"guess":"E","timestamp":1546269203},{"blank":true},{"blank":true},{"blank":true},{"confirmed":true,"guess":"B","timestamp":1546269203},{"confirmed":true,"guess":"E","timestamp":1546269203},{"confirmed":true,"guess":"E","timestamp":1546269203},{"confirmed":true,"guess":"R","timestamp":1546269203},{"confirmed":true,"guess":"T","timestamp":1546269203},{"confirmed":true,"guess":"A","timestamp":1546269203},{"confirmed":true,"guess":"P","timestamp":1546269203},{"blank":true},{"confirmed":true,"guess":"S","timestamp":1546269203},{"confirmed":true,"guess":"T","timestamp":1546269203},{"confirmed":true,"guess":"A","timestamp":1546269203},{"confirmed":true,"guess":"C","timestamp":1546269203},{"confirmed":true,"guess":"K","timestamp":1546269203},{"blank":true},{"confirmed":true,"guess":"M","timestamp":1546269203},{"confirmed":true,"guess":"A","timestamp":1546269203},{"checked":true,"guess":"Y","modified":true,"timestamp":1546269212},{"confirmed":true,"guess":"S","timestamp":1546269203},{"confirmed":true,"guess":"L","timestamp":1546269203},{"confirmed":true,"guess":"I","timestamp":1546269203},{"confirmed":true,"guess":"S","timestamp":1546269203},{"confirmed":true,"guess":"B","timestamp":1546269203},{"confirmed":true,"guess":"O","timestamp":1546269203},{"confirmed":true,"guess":"N","timestamp":1546269203},{"blank":true},{"blank":true},{"confirmed":true,"guess":"X","timestamp":1546269203},{"confirmed":true,"guess":"R","timestamp":1546269203},{"confirmed":true,"guess":"A","timestamp":1546269203},{"confirmed":true,"guess":"Y","timestamp":1546269203},{"blank":true},{"blank":true},{"confirmed":true,"guess":"H","timestamp":1546269203},{"confirmed":true,"guess":"I","timestamp":1546269203},{"confirmed":true,"guess":"R","timestamp":1546269203},{"confirmed":true,"guess":"A","timestamp":1546269203},{"confirmed":true,"guess":"B","timestamp":1546269203},{"confirmed":true,"guess":"L","timestamp":1546269203},{"confirmed":true,"guess":"E","timestamp":1546269203},{"confirmed":true,"guess":"P","timestamp":1546269203},{"confirmed":true,"guess":"O","timestamp":1546269203},{"confirmed":true,"guess":"P","timestamp":1546269203},{"confirmed":true,"guess":"Q","timestamp":1546269203},{"confirmed":true,"guess":"U","timestamp":1546269203},{"confirmed":true,"guess":"E","timestamp":1546269203},{"confirmed":true,"guess":"S","timestamp":1546269203},{"confirmed":true,"guess":"T","timestamp":1546269203},{"confirmed":true,"guess":"I","timestamp":1546269203},{"confirmed":true,"guess":"O","timestamp":1546269203},{"confirmed":true,"guess":"N","timestamp":1546269203},{"blank":true},{"confirmed":true,"guess":"N","timestamp":1546269203},{"confirmed":true,"guess":"E","timestamp":1546269203},{"confirmed":true,"guess":"A","timestamp":1546269203},{"confirmed":true,"guess":"R","timestamp":1546269203},{"confirmed":true,"guess":"E","timestamp":1546269203},{"confirmed":true,"guess":"R","timestamp":1546269203},{"blank":true},{"blank":true},{"blank":true},{"confirmed":true,"guess":"N","timestamp":1546269203},{"confirmed":true,"guess":"W","timestamp":1546269203},{"confirmed":true,"guess":"A","timestamp":1546269203},{"blank":true},{"confirmed":true,"guess":"F","timestamp":1546269203},{"confirmed":true,"guess":"E","timestamp":1546269203},{"confirmed":true,"guess":"A","timestamp":1546269203},{"confirmed":true,"guess":"R","timestamp":1546269203},{"blank":true},{"confirmed":true,"guess":"A","timestamp":1546269203},{"confirmed":true,"guess":"G","timestamp":1546269203},{"confirmed":true,"guess":"A","timestamp":1546269203},{"confirmed":true,"guess":"I","timestamp":1546269203},{"confirmed":true,"guess":"N","timestamp":1546269203},{"confirmed":true,"guess":"S","timestamp":1546269203},{"confirmed":true,"guess":"T","timestamp":1546269203},{"confirmed":true,"guess":"G","timestamp":1546269203},{"confirmed":true,"guess":"R","timestamp":1546269203},{"confirmed":true,"guess":"A","timestamp":1546269203},{"confirmed":true,"guess":"I","timestamp":1546269203},{"confirmed":true,"guess":"N","timestamp":1546269203},{"blank":true},{"confirmed":true,"guess":"A","timestamp":1546269203},{"confirmed":true,"guess":"R","timestamp":1546269203},{"confirmed":true,"guess":"K","timestamp":1546269203},{"blank":true},{"blank":true},{"confirmed":true,"guess":"F","timestamp":1546269203},{"confirmed":true,"guess":"I","timestamp":1546269203},{"confirmed":true,"guess":"L","timestamp":1546269203},{"confirmed":true,"guess":"M","timestamp":1546269203},{"blank":true},{"confirmed":true,"guess":"V","timestamp":1546269203},{"confirmed":true,"guess":"E","timestamp":1546269203},{"confirmed":true,"guess":"N","timestamp":1546269203},{"confirmed":true,"guess":"T","timestamp":1546269203},{"confirmed":true,"guess":"I","timestamp":1546269203},{"confirmed":true,"guess":"S","timestamp":1546269203},{"blank":true},{"confirmed":true,"guess":"M","timestamp":1546269203},{"confirmed":true,"guess":"M","timestamp":1546269203},{"confirmed":true,"guess":"I","timestamp":1546269203},{"blank":true},{"blank":true},{"confirmed":true,"guess":"E","timestamp":1546269203},{"confirmed":true,"guess":"N","timestamp":1546269203},{"confirmed":true,"guess":"A","timestamp":1546269203},{"confirmed":true,"guess":"M","timestamp":1546269203},{"confirmed":true,"guess":"E","timestamp":1546269203},{"confirmed":true,"guess":"L","timestamp":1546269203},{"confirmed":true,"guess":"S","timestamp":1546269203},{"blank":true},{"confirmed":true,"guess":"M","timestamp":1546269203},{"confirmed":true,"guess":"E","timestamp":1546269203},{"confirmed":true,"guess":"L","timestamp":1546269203},{"confirmed":true,"guess":"E","timestamp":1546269203},{"confirmed":true,"guess":"E","timestamp":1546269203},{"confirmed":true,"guess":"S","timestamp":1546269203},{"blank":true},{"confirmed":true,"guess":"H","timestamp":1546269203},{"confirmed":true,"guess":"Y","timestamp":1546269203},{"confirmed":true,"guess":"P","timestamp":1546269203},{"confirmed":true,"guess":"E","timestamp":1546269203},{"confirmed":true,"guess":"A","timestamp":1546269203},{"confirmed":true,"guess":"C","timestamp":1546269203},{"confirmed":true,"guess":"R","timestamp":1546269203},{"confirmed":true,"guess":"O","timestamp":1546269203},{"confirmed":true,"guess":"S","timestamp":1546269203},{"confirmed":true,"guess":"S","timestamp":1546269203},{"blank":true},{"confirmed":true,"guess":"L","timestamp":1546269203},{"confirmed":true,"guess":"A","timestamp":1546269203},{"confirmed":true,"guess":"R","timestamp":1546269203},{"confirmed":true,"guess":"I","timestamp":1546269203},{"confirmed":true,"guess":"S","timestamp":1546269203},{"confirmed":true,"guess":"S","timestamp":1546269203},{"confirmed":true,"guess":"A","timestamp":1546269203},{"blank":true},{"confirmed":true,"guess":"S","timestamp":1546269203},{"confirmed":true,"guess":"E","timestamp":1546269203},{"confirmed":true,"guess":"A","timestamp":1546269203},{"confirmed":true,"guess":"T","timestamp":1546269203},{"confirmed":true,"guess":"A","timestamp":1546269203},{"confirmed":true,"guess":"C","timestamp":1546269203},{"confirmed":true,"guess":"S","timestamp":1546269203},{"confirmed":true,"guess":"H","timestamp":1546269203},{"confirmed":true,"guess":"O","timestamp":1546269203},{"confirmed":true,"guess":"W","timestamp":1546269203},{"confirmed":true,"guess":"E","timestamp":1546269203},{"confirmed":true,"guess":"R","timestamp":1546269203},{"blank":true},{"confirmed":true,"guess":"S","timestamp":1546269203},{"confirmed":true,"guess":"T","timestamp":1546269203},{"confirmed":true,"guess":"U","timestamp":1546269203},{"confirmed":true,"guess":"N","timestamp":1546269203},{"confirmed":true,"guess":"T","timestamp":1546269203},{"confirmed":true,"guess":"E","timestamp":1546269203},{"confirmed":true,"guess":"D","timestamp":1546269203},{"blank":true},{"confirmed":true,"guess":"U","timestamp":1546269203},{"confirmed":true,"guess":"N","timestamp":1546269203},{"confirmed":true,"guess":"L","timestamp":1546269203},{"confirmed":true,"guess":"A","timestamp":1546269203},{"confirmed":true,"guess":"C","timestamp":1546269203},{"confirmed":true,"guess":"E","timestamp":1546269203},{"confirmed":true,"guess":"K","timestamp":1546269203},{"confirmed":true,"guess":"I","timestamp":1546269203},{"confirmed":true,"guess":"D","timestamp":1546269203},{"confirmed":true,"guess":"N","timestamp":1546269203},{"confirmed":true,"guess":"A","timestamp":1546269203},{"confirmed":true,"guess":"P","timestamp":1546269203},{"blank":true},{"blank":true},{"confirmed":true,"guess":"S","timestamp":1546269203},{"confirmed":true,"guess":"E","timestamp":1546269203},{"confirmed":true,"guess":"D","timestamp":1546269203},{"confirmed":true,"guess":"A","timestamp":1546269203},{"confirmed":true,"guess":"N","timestamp":1546269203},{"confirmed":true,"guess":"S","timestamp":1546269203},{"blank":true},{"confirmed":true,"guess":"E","timestamp":1546269203},{"confirmed":true,"guess":"V","timestamp":1546269203},{"confirmed":true,"guess":"E","timestamp":1546269203},{"confirmed":true,"guess":"N","timestamp":1546269203},{"confirmed":true,"guess":"T","timestamp":1546269203},{"confirmed":true,"guess":"S","timestamp":1546269203}]},"calcs":{"percentFilled":100,"secondsSpentSolving":1973,"solved":true},"firsts":{"checked":1546269208,"opened":1546132329,"solved":1546269212},"lastCommitID":"20B487","puzzleID":16160,"timestamp":1546269213,"userID":55348624,"lastSolve":1546269213}