{"board":{"cells":[{"confirmed":true,"guess":"C","timestamp":87196},{"confirmed":true,"guess":"O","timestamp":87196},{"confirmed":true,"guess":"A","timestamp":87196},{"confirmed":true,"guess":"R","timestamp":87196},{"confirmed":true,"guess":"S","timestamp":87196},{"confirmed":true,"guess":"E","timestamp":87196},{"blank":true},{"blank":true},{"blank":true},{"confirmed":true,"guess":"H","timestamp":87196},{"confirmed":true,"guess":"A","timestamp":87196},{"confirmed":true,"guess":"S","timestamp":87196},{"confirmed":true,"guess":"T","timestamp":87196},{"confirmed":true,"guess":"E","timestamp":87196},{"blank":true},{"blank":true},{"confirmed":true,"guess":"A","timestamp":87196},{"confirmed":true,"guess":"S","timestamp":87196},{"confirmed":true,"guess":"P","timestamp":87196},{"confirmed":true,"guess":"I","timestamp":87196},{"confirmed":true,"guess":"C","timestamp":87196},{"confirmed":true,"guess":"A","timestamp":87196},{"confirmed":true,"guess":"P","timestamp":87196},{"confirmed":true,"guess":"P","timestamp":87196},{"confirmed":true,"guess":"E","timestamp":87196},{"confirmed":true,"guess":"N","timestamp":87196},{"confirmed":true,"guess":"D","timestamp":87196},{"confirmed":true,"guess":"S","timestamp":87196},{"blank":true},{"confirmed":true,"guess":"C","timestamp":87196},{"confirmed":true,"guess":"O","timestamp":87196},{"confirmed":true,"guess":"S","timestamp":87196},{"confirmed":true,"guess":"S","timestamp":87196},{"confirmed":true,"guess":"E","timestamp":87196},{"confirmed":true,"guess":"T","timestamp":87196},{"blank":true},{"confirmed":true,"guess":"P","timestamp":87196},{"confirmed":true,"guess":"L","timestamp":87196},{"confirmed":true,"guess":"O","timestamp":87196},{"confirmed":true,"guess":"U","timestamp":87196},{"confirmed":true,"guess":"G","timestamp":87196},{"confirmed":true,"guess":"H","timestamp":87196},{"confirmed":true,"guess":"T","timestamp":87196},{"confirmed":true,"guess":"H","timestamp":87196},{"confirmed":true,"guess":"E","timestamp":87196},{"confirmed":true,"guess":"D","timestamp":87196},{"confirmed":true,"guess":"U","timestamp":87196},{"confirmed":true,"guess":"D","timestamp":87196},{"confirmed":true,"guess":"E","timestamp":87196},{"blank":true},{"confirmed":true,"guess":"R","timestamp":87196},{"confirmed":true,"guess":"A","timestamp":87196},{"confirmed":true,"guess":"H","timestamp":87196},{"confirmed":true,"guess":"R","timestamp":87196},{"confirmed":true,"guess":"A","timestamp":87196},{"confirmed":true,"guess":"H","timestamp":87196},{"blank":true},{"confirmed":true,"guess":"A","timestamp":87196},{"confirmed":true,"guess":"L","timestamp":87196},{"confirmed":true,"guess":"U","timestamp":87196},{"confirmed":true,"guess":"M","timestamp":87196},{"confirmed":true,"guess":"N","timestamp":87196},{"confirmed":true,"guess":"A","timestamp":87196},{"confirmed":true,"guess":"S","timestamp":87196},{"confirmed":true,"guess":"E","timestamp":87196},{"confirmed":true,"guess":"X","timestamp":87196},{"blank":true},{"confirmed":true,"guess":"G","timestamp":87196},{"confirmed":true,"guess":"A","timestamp":87196},{"confirmed":true,"guess":"L","timestamp":87196},{"confirmed":true,"guess":"L","timestamp":87196},{"confirmed":true,"guess":"E","timestamp":87196},{"confirmed":true,"guess":"R","timestamp":87196},{"confirmed":true,"guess":"Y","timestamp":87196},{"blank":true},{"confirmed":true,"guess":"M","timestamp":87196},{"confirmed":true,"guess":"I","timestamp":87196},{"confirmed":true,"guess":"S","timestamp":87196},{"confirmed":true,"guess":"T","timestamp":87196},{"blank":true},{"confirmed":true,"guess":"S","timestamp":87196},{"confirmed":true,"guess":"P","timestamp":87196},{"confirmed":true,"guess":"O","timestamp":87196},{"confirmed":true,"guess":"T","timestamp":87196},{"confirmed":true,"guess":"P","timestamp":87196},{"confirmed":true,"guess":"L","timestamp":87196},{"confirmed":true,"guess":"A","timestamp":87196},{"confirmed":true,"guess":"Y","timestamp":87196},{"blank":true},{"confirmed":true,"guess":"S","timestamp":87196},{"confirmed":true,"guess":"L","timestamp":87196},{"confirmed":true,"guess":"A","timestamp":87196},{"confirmed":true,"guess":"V","timestamp":87196},{"confirmed":true,"guess":"S","timestamp":87196},{"blank":true},{"confirmed":true,"guess":"R","timestamp":87196},{"confirmed":true,"guess":"O","timestamp":87196},{"confirmed":true,"guess":"O","timestamp":87196},{"confirmed":true,"guess":"T","timestamp":87196},{"confirmed":true,"guess":"E","timestamp":87196},{"confirmed":true,"guess":"D","timestamp":87196},{"blank":true},{"confirmed":true,"guess":"I","timestamp":87196},{"confirmed":true,"guess":"R","timestamp":87196},{"confirmed":true,"guess":"T","timestamp":87196},{"confirmed":true,"guess":"A","timestamp":87196},{"confirmed":true,"guess":"I","timestamp":87196},{"confirmed":true,"guess":"M","timestamp":87196},{"confirmed":true,"guess":"E","timestamp":87196},{"confirmed":true,"guess":"E","timestamp":87196},{"blank":true},{"blank":true},{"confirmed":true,"guess":"P","timestamp":87196},{"confirmed":true,"guess":"I","timestamp":87196},{"confirmed":true,"guess":"E","timestamp":87196},{"confirmed":true,"guess":"T","timestamp":87196},{"confirmed":true,"guess":"A","timestamp":87196},{"blank":true},{"confirmed":true,"guess":"P","timestamp":87196},{"confirmed":true,"guess":"A","timestamp":87196},{"confirmed":true,"guess":"L","timestamp":87196},{"confirmed":true,"guess":"M","timestamp":87196},{"confirmed":true,"guess":"T","timestamp":87196},{"confirmed":true,"guess":"R","timestamp":87196},{"confirmed":true,"guess":"E","timestamp":87196},{"confirmed":true,"guess":"E","timestamp":87196},{"confirmed":true,"guess":"W","timestamp":87196},{"confirmed":true,"guess":"A","timestamp":87196},{"confirmed":true,"guess":"S","timestamp":87196},{"confirmed":true,"guess":"A","timestamp":87196},{"confirmed":true,"guess":"T","timestamp":87196},{"confirmed":true,"guess":"C","timestamp":87196},{"confirmed":true,"guess":"H","timestamp":87196},{"blank":true},{"confirmed":true,"guess":"C","timestamp":87196},{"confirmed":true,"guess":"R","timestamp":87196},{"confirmed":true,"guess":"O","timestamp":87196},{"confirmed":true,"guess":"W","timestamp":87196},{"confirmed":true,"guess":"D","timestamp":87196},{"confirmed":true,"guess":"I","timestamp":87196},{"confirmed":true,"guess":"N","timestamp":87196},{"blank":true},{"confirmed":true,"guess":"C","timestamp":87196},{"confirmed":true,"guess":"H","timestamp":87196},{"confirmed":true,"guess":"O","timestamp":87196},{"confirmed":true,"guess":"I","timestamp":87196},{"confirmed":true,"guess":"R","timestamp":87196},{"blank":true},{"blank":true},{"blank":true},{"blank":true},{"confirmed":true,"guess":"C","timestamp":87196},{"confirmed":true,"guess":"H","timestamp":87196},{"confirmed":true,"guess":"A","timestamp":87196},{"confirmed":true,"guess":"S","timestamp":87196},{"confirmed":true,"guess":"E","timestamp":87196},{"blank":true},{"confirmed":true,"guess":"P","timestamp":87196},{"confirmed":true,"guess":"R","timestamp":87196},{"confirmed":true,"guess":"E","timestamp":87196},{"confirmed":true,"guess":"A","timestamp":87196},{"confirmed":true,"guess":"C","timestamp":87196},{"confirmed":true,"guess":"H","timestamp":87196},{"blank":true},{"confirmed":true,"guess":"E","timestamp":87196},{"confirmed":true,"guess":"N","timestamp":87196},{"confirmed":true,"guess":"T","timestamp":87196},{"blank":true},{"confirmed":true,"guess":"C","timestamp":87196},{"confirmed":true,"guess":"U","timestamp":87196},{"confirmed":true,"guess":"T","timestamp":87196},{"confirmed":true,"guess":"S","timestamp":87196},{"blank":true},{"confirmed":true,"guess":"O","timestamp":87196},{"confirmed":true,"guess":"U","timestamp":87196},{"confirmed":true,"guess":"T","timestamp":87196},{"confirmed":true,"guess":"S","timestamp":87196},{"confirmed":true,"guess":"E","timestamp":87196},{"confirmed":true,"guess":"T","timestamp":87196},{"blank":true},{"confirmed":true,"guess":"I","timestamp":87196},{"confirmed":true,"guess":"N","timestamp":87196},{"confirmed":true,"guess":"H","timestamp":87196},{"confirmed":true,"guess":"E","timestamp":87196},{"confirmed":true,"guess":"L","timestamp":87196},{"confirmed":true,"guess":"L","timestamp":87196},{"blank":true},{"blank":true},{"blank":true},{"confirmed":true,"guess":"A","timestamp":87196},{"confirmed":true,"guess":"L","timestamp":87196},{"confirmed":true,"guess":"A","timestamp":87196},{"confirmed":true,"guess":"C","timestamp":87196},{"confirmed":true,"guess":"R","timestamp":87196},{"confirmed":true,"guess":"I","timestamp":87196},{"confirmed":true,"guess":"T","timestamp":87196},{"confirmed":true,"guess":"Y","timestamp":87196},{"blank":true},{"confirmed":true,"guess":"R","timestamp":87196},{"confirmed":true,"guess":"E","timestamp":87196},{"confirmed":true,"guess":"P","timestamp":87196},{"confirmed":true,"guess":"O","timestamp":87196},{"blank":true},{"blank":true},{"confirmed":true,"guess":"R","timestamp":87196},{"confirmed":true,"guess":"U","timestamp":87196},{"confirmed":true,"guess":"B","timestamp":87196},{"confirmed":true,"guess":"O","timestamp":87196},{"confirmed":true,"guess":"F","timestamp":87196},{"confirmed":true,"guess":"F","timestamp":87196},{"confirmed":true,"guess":"B","timestamp":87196},{"confirmed":true,"guess":"A","timestamp":87196},{"confirmed":true,"guess":"S","timestamp":87196},{"confirmed":true,"guess":"R","timestamp":87196},{"confirmed":true,"guess":"A","timestamp":87196},{"blank":true},{"confirmed":true,"guess":"E","timestamp":87196},{"confirmed":true,"guess":"X","timestamp":87196},{"confirmed":true,"guess":"P","timestamp":87196},{"confirmed":true,"guess":"O","timestamp":87196},{"confirmed":true,"guess":"N","timestamp":87196},{"confirmed":true,"guess":"E","timestamp":87196},{"confirmed":true,"guess":"N","timestamp":87196},{"confirmed":true,"guess":"T","timestamp":87196},{"confirmed":true,"guess":"S","timestamp":87196},{"blank":true},{"confirmed":true,"guess":"N","timestamp":87196},{"confirmed":true,"guess":"O","timestamp":87196},{"confirmed":true,"guess":"L","timestamp":87196},{"confirmed":true,"guess":"I","timestamp":87196},{"confirmed":true,"guess":"E","timestamp":87196},{"confirmed":true,"guess":"S","timestamp":87196},{"confirmed":true,"guess":"N","timestamp":87196},{"confirmed":true,"guess":"E","timestamp":87196},{"confirmed":true,"guess":"E","timestamp":87196},{"confirmed":true,"guess":"Z","timestamp":87196},{"confirmed":true,"guess":"Y","timestamp":87196},{"blank":true},{"blank":true},{"confirmed":true,"guess":"I","timestamp":87196},{"confirmed":true,"guess":"S","timestamp":87196},{"confirmed":true,"guess":"L","timestamp":87196},{"confirmed":true,"guess":"E","timestamp":87196},{"blank":true},{"confirmed":true,"guess":"O","timestamp":87196},{"confirmed":true,"guess":"I","timestamp":87196},{"confirmed":true,"guess":"N","timestamp":87196},{"confirmed":true,"guess":"T","timestamp":87196},{"confirmed":true,"guess":"M","timestamp":87196},{"confirmed":true,"guess":"E","revealed":true,"timestamp":87196},{"confirmed":true,"guess":"N","timestamp":87196},{"confirmed":true,"guess":"T","timestamp":87196},{"blank":true},{"blank":true},{"blank":true},{"confirmed":true,"guess":"A","timestamp":87196},{"confirmed":true,"guess":"Z","timestamp":87196},{"confirmed":true,"guess":"A","timestamp":87196},{"confirmed":true,"guess":"L","timestamp":87196},{"confirmed":true,"guess":"E","timestamp":87196},{"confirmed":true,"guess":"A","timestamp":87196},{"blank":true},{"confirmed":true,"guess":"I","timestamp":87196},{"confirmed":true,"guess":"N","timestamp":87196},{"confirmed":true,"guess":"S","timestamp":87196},{"confirmed":true,"guess":"O","timestamp":87196},{"confirmed":true,"guess":"L","timestamp":87196},{"confirmed":true,"guess":"E","timestamp":87196},{"blank":true},{"confirmed":true,"guess":"B","timestamp":87196},{"confirmed":true,"guess":"O","timestamp":87196},{"confirmed":true,"guess":"N","timestamp":87196},{"confirmed":true,"guess":"E","timestamp":87196},{"blank":true},{"confirmed":true,"guess":"T","timestamp":87196},{"confirmed":true,"guess":"A","timestamp":87196},{"confirmed":true,"guess":"M","timestamp":87196},{"blank":true},{"confirmed":true,"guess":"W","timestamp":87196},{"confirmed":true,"guess":"O","timestamp":87196},{"confirmed":true,"guess":"L","timestamp":87196},{"confirmed":true,"guess":"V","timestamp":87196},{"confirmed":true,"guess":"E","timestamp":87196},{"confirmed":true,"guess":"S","timestamp":87196},{"blank":true},{"confirmed":true,"guess":"C","timestamp":87196},{"confirmed":true,"guess":"L","timestamp":87196},{"confirmed":true,"guess":"O","timestamp":87196},{"confirmed":true,"guess":"S","timestamp":87196},{"confirmed":true,"guess":"E","timestamp":87196},{"blank":true},{"blank":true},{"blank":true},{"blank":true},{"confirmed":true,"guess":"T","timestamp":87196},{"confirmed":true,"guess":"H","timestamp":87196},{"confirmed":true,"guess":"R","timestamp":87196},{"confirmed":true,"guess":"E","timestamp":87196},{"confirmed":true,"guess":"W","timestamp":87196},{"blank":true},{"confirmed":true,"guess":"S","timestamp":87196},{"confirmed":true,"guess":"M","timestamp":87196},{"confirmed":true,"guess":"E","timestamp":87196},{"confirmed":true,"guess":"L","timestamp":87196},{"confirmed":true,"guess":"T","timestamp":87196},{"confirmed":true,"guess":"E","timestamp":87196},{"confirmed":true,"guess":"R","timestamp":87196},{"blank":true},{"confirmed":true,"guess":"S","timestamp":87196},{"confirmed":true,"guess":"T","timestamp":87196},{"confirmed":true,"guess":"P","timestamp":87196},{"confirmed":true,"guess":"E","timestamp":87196},{"confirmed":true,"guess":"T","timestamp":87196},{"confirmed":true,"guess":"E","timestamp":87196},{"confirmed":true,"guess":"R","timestamp":87196},{"confirmed":true,"guess":"R","timestamp":87196},{"confirmed":true,"guess":"E","timestamp":87196},{"confirmed":true,"guess":"T","timestamp":87196},{"confirmed":true,"guess":"R","timestamp":87196},{"confirmed":true,"guess":"E","timestamp":87196},{"confirmed":true,"guess":"A","timestamp":87196},{"confirmed":true,"guess":"T","timestamp":87196},{"confirmed":true,"guess":"S","timestamp":87196},{"blank":true},{"confirmed":true,"guess":"A","timestamp":87196},{"confirmed":true,"guess":"S","timestamp":87196},{"confirmed":true,"guess":"S","timestamp":87196},{"confirmed":true,"guess":"A","timestamp":87196},{"confirmed":true,"guess":"M","timestamp":87196},{"blank":true},{"blank":true},{"confirmed":true,"guess":"S","timestamp":87196},{"confirmed":true,"guess":"N","timestamp":87196},{"confirmed":true,"guess":"A","timestamp":87196},{"confirmed":true,"guess":"R","timestamp":87196},{"confirmed":true,"guess":"E","timestamp":87196},{"confirmed":true,"guess":"I","timestamp":87196},{"confirmed":true,"guess":"F","timestamp":87196},{"confirmed":true,"guess":"S","timestamp":87196},{"blank":true},{"confirmed":true,"guess":"B","timestamp":87196},{"confirmed":true,"guess":"O","timestamp":87196},{"confirmed":true,"guess":"T","timestamp":87196},{"confirmed":true,"guess":"T","timestamp":87196},{"confirmed":true,"guess":"O","timestamp":87196},{"confirmed":true,"guess":"M","timestamp":87196},{"blank":true},{"confirmed":true,"guess":"S","timestamp":87196},{"confirmed":true,"guess":"W","timestamp":87196},{"confirmed":true,"guess":"A","timestamp":87196},{"confirmed":true,"guess":"B","timestamp":87196},{"confirmed":true,"guess":"S","timestamp":87196},{"blank":true},{"confirmed":true,"guess":"C","timestamp":87196},{"confirmed":true,"guess":"L","timestamp":87196},{"confirmed":true,"guess":"U","timestamp":87196},{"confirmed":true,"guess":"B","timestamp":87196},{"confirmed":true,"guess":"R","timestamp":87196},{"confirmed":true,"guess":"A","timestamp":87196},{"confirmed":true,"guess":"C","timestamp":87196},{"confirmed":true,"guess":"E","timestamp":87196},{"blank":true},{"confirmed":true,"guess":"K","timestamp":87196},{"confirmed":true,"guess":"O","timestamp":87196},{"confirmed":true,"guess":"R","timestamp":87196},{"confirmed":true,"guess":"N","timestamp":87196},{"blank":true},{"confirmed":true,"guess":"W","timestamp":87196},{"confirmed":true,"guess":"E","timestamp":87196},{"confirmed":true,"guess":"L","timestamp":87196},{"confirmed":true,"guess":"C","timestamp":87196},{"confirmed":true,"guess":"O","timestamp":87196},{"confirmed":true,"guess":"M","timestamp":87196},{"confirmed":true,"guess":"E","timestamp":87196},{"blank":true},{"confirmed":true,"guess":"E","timestamp":87196},{"confirmed":true,"guess":"D","timestamp":87196},{"confirmed":true,"guess":"U","timestamp":87196},{"confirmed":true,"guess":"E","timestamp":87196},{"confirmed":true,"guess":"T","timestamp":87196},{"confirmed":true,"guess":"A","timestamp":87196},{"confirmed":true,"guess":"L","timestamp":87196},{"confirmed":true,"guess":"I","timestamp":87196},{"confirmed":true,"guess":"A","timestamp":87196},{"blank":true},{"confirmed":true,"guess":"E","timestamp":87196},{"confirmed":true,"guess":"L","timestamp":87196},{"confirmed":true,"guess":"A","timestamp":87196},{"confirmed":true,"guess":"I","timestamp":87196},{"confirmed":true,"guess":"N","timestamp":87196},{"confirmed":true,"guess":"E","timestamp":87196},{"blank":true},{"confirmed":true,"guess":"N","timestamp":87196},{"confirmed":true,"guess":"E","timestamp":87196},{"confirmed":true,"guess":"A","timestamp":87196},{"confirmed":true,"guess":"T","timestamp":87196},{"confirmed":true,"guess":"N","timestamp":87196},{"confirmed":true,"guess":"I","timestamp":87196},{"confirmed":true,"guess":"K","timestamp":87196},{"confirmed":true,"guess":"M","timestamp":87196},{"confirmed":true,"guess":"E","timestamp":87196},{"confirmed":true,"guess":"M","timestamp":87196},{"confirmed":true,"guess":"O","timestamp":87196},{"confirmed":true,"guess":"R","timestamp":87196},{"confirmed":true,"guess":"Y","timestamp":87196},{"blank":true},{"confirmed":true,"guess":"E","timestamp":87196},{"confirmed":true,"guess":"A","timestamp":87196},{"confirmed":true,"guess":"R","timestamp":87196},{"confirmed":true,"guess":"N","timestamp":87196},{"confirmed":true,"guess":"E","timestamp":87196},{"confirmed":true,"guess":"D","timestamp":87196},{"blank":true},{"confirmed":true,"guess":"G","timestamp":87196},{"confirmed":true,"guess":"A","timestamp":87196},{"confirmed":true,"guess":"V","timestamp":87196},{"confirmed":true,"guess":"O","timestamp":87196},{"confirmed":true,"guess":"T","timestamp":87196},{"confirmed":true,"guess":"T","timestamp":87196},{"confirmed":true,"guess":"E","timestamp":87196},{"confirmed":true,"guess":"E","timestamp":87196},{"confirmed":true,"guess":"S","timestamp":87196},{"confirmed":true,"guess":"S","timestamp":87196},{"confirmed":true,"guess":"I","timestamp":87196},{"confirmed":true,"guess":"E","timestamp":87196},{"blank":true},{"blank":true},{"confirmed":true,"guess":"T","timestamp":87196},{"confirmed":true,"guess":"Y","timestamp":87196},{"confirmed":true,"guess":"K","timestamp":87196},{"confirmed":true,"guess":"E","timestamp":87196},{"confirmed":true,"guess":"S","timestamp":87196},{"blank":true},{"blank":true},{"blank":true},{"confirmed":true,"guess":"R","timestamp":87196},{"confirmed":true,"guess":"E","timestamp":87196},{"confirmed":true,"guess":"E","timestamp":87196},{"confirmed":true,"guess":"S","timestamp":87196},{"confirmed":true,"guess":"E","timestamp":87196},{"confirmed":true,"guess":"S","timestamp":87196}]},"calcs":{"percentFilled":100,"secondsSpentSolving":1444,"solved":true},"firsts":{"opened":1593299974,"revealed":1593387178,"solved":1593387178},"lastCommitID":"qu8o21","puzzleID":18356,"timestamp":1593387178,"userID":55348624,"minGuessTime":1593299982,"lastSolve":1593387178}