{"board":{"cells":[{"guess":"D","timestamp":1625976480},{"guess":"R","timestamp":1625976480},{"guess":"E","timestamp":1625976481},{"guess":"S","timestamp":1625976481},{"guess":"S","timestamp":1625976481},{"guess":"A","timestamp":1625976481},{"guess":"G","timestamp":1625976504},{"guess":"E","timestamp":1625976481},{"blank":true},{"guess":"M","timestamp":1625977682},{"guess":"Y","timestamp":1625977546},{"guess":"B","timestamp":1625977674},{"guess":"A","timestamp":1625977681},{"guess":"D","timestamp":1625977577},{"blank":true},{"guess":"N","timestamp":1625976658},{"guess":"A","timestamp":1625977342},{"guess":"P","timestamp":1625977598},{"guess":"L","timestamp":1625977603},{"guess":"E","timestamp":1625977630},{"guess":"S","timestamp":1625977631},{"guess":"R","timestamp":1625976574},{"guess":"E","timestamp":1625976527},{"guess":"S","timestamp":1625977500},{"guess":"T","timestamp":1625977500},{"guess":"A","timestamp":1625977501},{"guess":"T","timestamp":1625976497},{"guess":"E","timestamp":1625976567},{"guess":"D","timestamp":1625976486},{"blank":true},{"guess":"C","timestamp":1625977688},{"guess":"O","timestamp":1625977546},{"guess":"U","timestamp":1625977675},{"guess":"L","timestamp":1625977681},{"guess":"D","timestamp":1625977577},{"blank":true},{"guess":"O","timestamp":1625976658},{"guess":"M","timestamp":1625977343},{"guess":"E","timestamp":1625977593},{"guess":"A","timestamp":1625977593},{"guess":"R","timestamp":1625977593},{"guess":"A","timestamp":1625977635},{"guess":"U","timestamp":1625976576},{"guess":"N","timestamp":1625976527},{"guess":"P","timestamp":1625977514},{"guess":"O","timestamp":1625977511},{"guess":"I","timestamp":1625977513},{"guess":"S","timestamp":1625976498},{"guess":"E","timestamp":1625976586},{"guess":"D","timestamp":1625976486},{"blank":true},{"guess":"B","timestamp":1625977638},{"guess":"U","timestamp":1625977547},{"guess":"R","timestamp":1625977638},{"guess":"D","timestamp":1625977638},{"guess":"E","timestamp":1625977579},{"guess":"N","timestamp":1625977627},{"guess":"O","timestamp":1625976658},{"guess":"F","timestamp":1625977344},{"guess":"P","timestamp":1625977598},{"guess":"O","timestamp":1625977604},{"guess":"O","timestamp":1625977640},{"guess":"F","timestamp":1625977636},{"guess":"G","timestamp":1625976576},{"guess":"O","timestamp":1625976527},{"guess":"O","timestamp":1625977523},{"guess":"P","timestamp":1625977511},{"guess":"D","timestamp":1625977526},{"guess":"Y","timestamp":1625976721},{"guess":"N","timestamp":1625977536},{"guess":"A","timestamp":1625976486},{"guess":"M","timestamp":1625977537},{"guess":"I","timestamp":1625977538},{"guess":"C","timestamp":1625977538},{"guess":"S","timestamp":1625977538},{"blank":true},{"blank":true},{"guess":"E","timestamp":1625977612},{"guess":"N","timestamp":1625976659},{"guess":"M","timestamp":1625977345},{"guess":"A","timestamp":1625977599},{"guess":"S","timestamp":1625977607},{"guess":"S","timestamp":1625977607},{"guess":"E","timestamp":1625977608},{"blank":true},{"blank":true},{"blank":true},{"blank":true},{"guess":"S","timestamp":1625977532},{"guess":"M","timestamp":1625976721},{"guess":"A","timestamp":1625977554},{"blank":true},{"guess":"E","timestamp":1625976646},{"guess":"T","timestamp":1625976646},{"guess":"A","timestamp":1625976647},{"blank":true},{"guess":"P","timestamp":1625976677},{"guess":"E","timestamp":1625976677},{"guess":"T","timestamp":1625976676},{"guess":"E","timestamp":1625976659},{"guess":"R","timestamp":1625976677},{"blank":true},{"blank":true},{"blank":true},{"blank":true},{"guess":"O","timestamp":1625976952},{"guess":"D","timestamp":1625976941},{"guess":"D","timestamp":1625976954},{"guess":"J","timestamp":1625976957},{"guess":"O","timestamp":1625976957},{"guess":"B","timestamp":1625976722},{"blank":true},{"guess":"B","timestamp":1625976845},{"guess":"R","timestamp":1625977699},{"guess":"E","timestamp":1625977699},{"guess":"N","timestamp":1625977548},{"guess":"D","timestamp":1625976749},{"guess":"A","timestamp":1625977563},{"guess":"N","timestamp":1625976741},{"blank":true},{"guess":"R","timestamp":1625976658},{"guess":"A","timestamp":1625976695},{"guess":"M","timestamp":1625976695},{"guess":"P","timestamp":1625976695},{"guess":"E","timestamp":1625976695},{"guess":"D","timestamp":1625976697},{"guess":"T","timestamp":1625976953},{"guess":"E","timestamp":1625976941},{"guess":"R","timestamp":1625976962},{"guess":"I","timestamp":1625976965},{"blank":true},{"guess":"O","timestamp":1625976720},{"guess":"D","timestamp":1625976712},{"guess":"E","timestamp":1625976713},{"blank":true},{"guess":"S","timestamp":1625976735},{"guess":"T","timestamp":1625976735},{"guess":"I","timestamp":1625976735},{"guess":"L","timestamp":1625976736},{"guess":"T","timestamp":1625976736},{"guess":"S","timestamp":1625976737},{"blank":true},{"guess":"D","timestamp":1625977346},{"guess":"R","timestamp":1625977402},{"guess":"A","timestamp":1625976703},{"guess":"C","timestamp":1625976700},{"guess":"O","timestamp":1625977389},{"guess":"I","timestamp":1625976756},{"guess":"A","timestamp":1625976756},{"guess":"M","timestamp":1625976757},{"guess":"M","timestamp":1625976757},{"guess":"A","timestamp":1625976757},{"guess":"L","timestamp":1625976720},{"guess":"A","timestamp":1625976716},{"guess":"L","timestamp":1625976757},{"guess":"A","timestamp":1625976757},{"blank":true},{"guess":"H","timestamp":1625976766},{"guess":"E","timestamp":1625976748},{"guess":"A","timestamp":1625976766},{"guess":"R","timestamp":1625976768},{"guess":"T","timestamp":1625976737},{"blank":true},{"guess":"I","timestamp":1625977347},{"guess":"M","timestamp":1625977409},{"guess":"R","timestamp":1625976703},{"guess":"A","timestamp":1625976700},{"guess":"N","timestamp":1625977390},{"guess":"S","timestamp":1625976953},{"guess":"L","timestamp":1625976941},{"guess":"O","timestamp":1625976937},{"guess":"M","timestamp":1625976967},{"guess":"O","timestamp":1625976968},{"blank":true},{"guess":"M","timestamp":1625976716},{"guess":"I","timestamp":1625976843},{"guess":"L","timestamp":1625976840},{"guess":"W","timestamp":1625976835},{"guess":"A","timestamp":1625976848},{"guess":"U","timestamp":1625976749},{"guess":"K","timestamp":1625976849},{"guess":"E","timestamp":1625976851},{"guess":"E","timestamp":1625976738},{"guess":"B","timestamp":1625977044},{"guess":"O","timestamp":1625977347},{"guess":"O","timestamp":1625977398},{"guess":"E","timestamp":1625976703},{"guess":"R","timestamp":1625976700},{"guess":"S","timestamp":1625976698},{"blank":true},{"guess":"S","timestamp":1625976783},{"guess":"M","timestamp":1625976924},{"guess":"O","timestamp":1625976924},{"guess":"K","timestamp":1625976925},{"guess":"E","timestamp":1625976897},{"blank":true},{"guess":"E","timestamp":1625976827},{"guess":"V","timestamp":1625976828},{"guess":"E","timestamp":1625976828},{"guess":"N","timestamp":1625976829},{"blank":true},{"blank":true},{"guess":"E","timestamp":1625976862},{"guess":"E","timestamp":1625976862},{"guess":"L","timestamp":1625976863},{"blank":true},{"guess":"J","timestamp":1625976886},{"guess":"E","timestamp":1625976703},{"guess":"D","timestamp":1625976700},{"blank":true},{"blank":true},{"blank":true},{"blank":true},{"guess":"R","timestamp":1625976889},{"guess":"I","timestamp":1625976890},{"guess":"C","timestamp":1625976890},{"guess":"K","timestamp":1625976892},{"blank":true},{"guess":"A","timestamp":1625976839},{"guess":"D","timestamp":1625976837},{"guess":"D","timestamp":1625976977},{"guess":"E","timestamp":1625976977},{"guess":"R","timestamp":1625976978},{"blank":true},{"guess":"P","timestamp":1625976738},{"guess":"O","timestamp":1625976990},{"guess":"P","timestamp":1625976990},{"guess":"O","timestamp":1625976991},{"blank":true},{"blank":true},{"blank":true},{"blank":true},{"guess":"S","timestamp":1625977008},{"guess":"S","timestamp":1625977008},{"guess":"R","timestamp":1625977009},{"blank":true},{"guess":"I","timestamp":1625976899},{"guess":"T","timestamp":1625976893},{"guess":"O","timestamp":1625977025},{"blank":true},{"blank":true},{"guess":"L","timestamp":1625977031},{"guess":"O","timestamp":1625976983},{"guess":"A","timestamp":1625976979},{"guess":"F","timestamp":1625977033},{"blank":true},{"guess":"T","timestamp":1625977038},{"guess":"O","timestamp":1625977000},{"guess":"R","timestamp":1625977039},{"guess":"S","timestamp":1625977040},{"guess":"O","timestamp":1625977040},{"blank":true},{"guess":"T","timestamp":1625977138},{"guess":"A","timestamp":1625977138},{"guess":"M","timestamp":1625977015},{"guess":"I","timestamp":1625977010},{"guess":"N","timestamp":1625977077},{"guess":"G","timestamp":1625976900},{"guess":"O","timestamp":1625976893},{"guess":"F","timestamp":1625977139},{"guess":"T","timestamp":1625977088},{"guess":"H","timestamp":1625977091},{"guess":"E","timestamp":1625977140},{"guess":"S","timestamp":1625976984},{"guess":"H","timestamp":1625976979},{"guess":"O","timestamp":1625977034},{"guess":"O","timestamp":1625977119},{"blank":true},{"guess":"L","timestamp":1625977000},{"guess":"I","timestamp":1625977054},{"guess":"T","timestamp":1625977055},{"guess":"H","timestamp":1625977055},{"guess":"E","timestamp":1625977056},{"guess":"A","timestamp":1625977072},{"guess":"R","timestamp":1625977073},{"guess":"I","timestamp":1625977015},{"guess":"S","timestamp":1625977011},{"guess":"E","timestamp":1625977074},{"blank":true},{"guess":"W","timestamp":1625976894},{"guess":"Y","timestamp":1625977083},{"guess":"A","timestamp":1625977083},{"guess":"T","timestamp":1625977084},{"guess":"T","timestamp":1625977085},{"blank":true},{"guess":"M","timestamp":1625976980},{"guess":"I","timestamp":1625977034},{"guess":"N","timestamp":1625977106},{"guess":"U","timestamp":1625977106},{"guess":"S","timestamp":1625977001},{"guess":"S","timestamp":1625977106},{"guess":"I","timestamp":1625977063},{"guess":"G","timestamp":1625977060},{"guess":"N","timestamp":1625977108},{"guess":"R","timestamp":1625977129},{"guess":"A","timestamp":1625977129},{"guess":"Z","timestamp":1625977016},{"guess":"O","timestamp":1625977131},{"guess":"R","timestamp":1625977078},{"blank":true},{"guess":"N","timestamp":1625976895},{"guess":"O","timestamp":1625977126},{"guess":"R","timestamp":1625977088},{"guess":"T","timestamp":1625977091},{"guess":"H","timestamp":1625977126},{"guess":"S","timestamp":1625977127},{"blank":true},{"guess":"L","timestamp":1625977034},{"guess":"O","timestamp":1625977119},{"guess":"N","timestamp":1625977426},{"blank":true},{"guess":"I","timestamp":1625977122},{"guess":"C","timestamp":1625977064},{"guess":"E","timestamp":1625977061},{"guess":"R","timestamp":1625977122},{"guess":"T","timestamp":1625977137},{"guess":"H","timestamp":1625977143},{"guess":"E","timestamp":1625977016},{"guess":"N","timestamp":1625977145},{"guess":"F","timestamp":1625977079},{"guess":"L","timestamp":1625977148},{"blank":true},{"guess":"R","timestamp":1625977277},{"guess":"E","timestamp":1625977088},{"guess":"P","timestamp":1625977091},{"guess":"E","timestamp":1625977280},{"guess":"A","timestamp":1625977173},{"guess":"L","timestamp":1625977171},{"guess":"S","timestamp":1625977035},{"blank":true},{"guess":"D","timestamp":1625977156},{"guess":"O","timestamp":1625977157},{"guess":"N","timestamp":1625977159},{"guess":"K","timestamp":1625977064},{"guess":"E","timestamp":1625977061},{"guess":"Y","timestamp":1625977153},{"blank":true},{"blank":true},{"blank":true},{"blank":true},{"guess":"B","timestamp":1625977288},{"guess":"A","timestamp":1625977288},{"guess":"R","timestamp":1625977289},{"guess":"E","timestamp":1625977279},{"guess":"S","timestamp":1625977088},{"blank":true},{"guess":"T","timestamp":1625977165},{"guess":"M","timestamp":1625977165},{"guess":"I","timestamp":1625977167},{"blank":true},{"guess":"S","timestamp":1625977489},{"guess":"E","timestamp":1625977428},{"guess":"N","timestamp":1625977483},{"blank":true},{"blank":true},{"blank":true},{"blank":true},{"guess":"I","timestamp":1625977304},{"guess":"M","timestamp":1625977209},{"guess":"I","timestamp":1625977305},{"guess":"T","timestamp":1625977301},{"guess":"A","timestamp":1625977223},{"guess":"T","timestamp":1625977306},{"guess":"E","timestamp":1625977289},{"blank":true},{"blank":true},{"guess":"B","timestamp":1625977246},{"guess":"O","timestamp":1625977251},{"guess":"O","timestamp":1625977173},{"guess":"T","timestamp":1625977478},{"guess":"S","timestamp":1625977478},{"guess":"T","timestamp":1625977479},{"guess":"R","timestamp":1625977428},{"guess":"E","timestamp":1625977480},{"guess":"N","timestamp":1625977444},{"guess":"G","timestamp":1625977448},{"guess":"T","timestamp":1625977452},{"guess":"H","timestamp":1625977457},{"guess":"P","timestamp":1625977292},{"guess":"E","timestamp":1625977210},{"guess":"N","timestamp":1625977292},{"guess":"E","timestamp":1625977294},{"guess":"L","timestamp":1625977224},{"guess":"O","timestamp":1625977295},{"guess":"P","timestamp":1625977291},{"guess":"E","timestamp":1625977239},{"guess":"C","timestamp":1625977242},{"guess":"O","timestamp":1625977246},{"guess":"O","timestamp":1625977258},{"guess":"S","timestamp":1625977175},{"blank":true},{"guess":"E","timestamp":1625977472},{"guess":"U","timestamp":1625977473},{"guess":"P","timestamp":1625977429},{"guess":"H","timestamp":1625977474},{"guess":"O","timestamp":1625977445},{"guess":"R","timestamp":1625977449},{"guess":"I","timestamp":1625977452},{"guess":"A","timestamp":1625977458},{"guess":"S","timestamp":1625977198},{"guess":"A","timestamp":1625977199},{"guess":"G","timestamp":1625977199},{"guess":"E","timestamp":1625977204},{"guess":"L","timestamp":1625977199},{"guess":"Y","timestamp":1625977200},{"blank":true},{"guess":"S","timestamp":1625977239},{"guess":"O","timestamp":1625977242},{"guess":"R","timestamp":1625977247},{"guess":"T","timestamp":1625977265},{"guess":"A","timestamp":1625977175},{"blank":true},{"guess":"E","timestamp":1625977493},{"guess":"M","timestamp":1625977491},{"guess":"A","timestamp":1625977429},{"guess":"I","timestamp":1625977482},{"guess":"L","timestamp":1625977445},{"guess":"I","timestamp":1625977449},{"guess":"N","timestamp":1625977452},{"guess":"G","timestamp":1625977459},{"guess":"O","timestamp":1625977218},{"guess":"D","timestamp":1625977210},{"guess":"E","timestamp":1625977218},{"guess":"S","timestamp":1625977204},{"guess":"S","timestamp":1625977220},{"guess":"A","timestamp":1625977202},{"blank":true},{"guess":"O","timestamp":1625977237},{"guess":"P","timestamp":1625977243},{"guess":"A","timestamp":1625977245},{"guess":"H","timestamp":1625977262},{"guess":"S","timestamp":1625977176},{"blank":true},{"guess":"N","timestamp":1625977495},{"guess":"P","timestamp":1625977491},{"guess":"R","timestamp":1625977430},{"guess":"T","timestamp":1625977465},{"guess":"O","timestamp":1625977445},{"guess":"T","timestamp":1625977450},{"guess":"E","timestamp":1625977453},{"guess":"S","timestamp":1625977462}]},"calcs":{"percentFilled":100,"secondsSpentSolving":1219,"solved":true},"firsts":{"opened":1625976470,"solved":1625977699},"lastCommitID":"768D2A","puzzleID":19361,"timestamp":1625977700,"userID":55348624,"lastSolve":1625977700}