{"board":{"cells":[{"blank":true},{"guess":"F","timestamp":78},{"guess":"O","timestamp":12},{"guess":"R","timestamp":58},{"guess":"E","timestamp":5182},{"guess":"S","timestamp":5183},{"guess":"A","timestamp":5183},{"guess":"W","timestamp":39},{"blank":true},{"blank":true},{},{"guess":"H","timestamp":5409},{},{"timestamp":5441},{},{"guess":"F","timestamp":1},{"guess":"I","timestamp":1},{"guess":"N","timestamp":2},{"guess":"A","timestamp":2},{"guess":"L","timestamp":2},{"guess":"E","timestamp":3},{"guess":"X","timestamp":3},{"guess":"A","timestamp":3},{"guess":"M","timestamp":4},{"blank":true},{},{"guess":"I","timestamp":5409},{},{"timestamp":5441},{},{"guess":"O","timestamp":5},{"guess":"N","timestamp":52},{"guess":"T","timestamp":13},{"guess":"H","timestamp":53},{"guess":"E","timestamp":54},{"timestamp":5206},{"timestamp":70793},{"guess":"N","timestamp":40},{},{"blank":true},{},{"guess":"L","timestamp":5410},{},{"timestamp":5441},{},{"guess":"R","timestamp":6},{"guess":"E","timestamp":63},{"guess":"A","timestamp":13},{"blank":true},{"guess":"G","timestamp":38758},{"timestamp":5205},{},{"blank":true},{"guess":"S","timestamp":70810},{"guess":"W","timestamp":70810},{"guess":"E","timestamp":70810},{"guess":"L","timestamp":5410},{"guess":"L","timestamp":70811},{"guess":"U","timestamp":70811},{"guess":"P","timestamp":70812},{"guess":"B","timestamp":6},{"guess":"A","timestamp":78},{"guess":"R","timestamp":14},{"guess":"M","timestamp":38755},{"guess":"Y","timestamp":38758},{"blank":true},{"blank":true},{},{},{},{},{"blank":true},{"timestamp":126640885},{"timestamp":126640885},{},{"guess":"E","timestamp":6},{"guess":"R","timestamp":73},{"guess":"I","timestamp":14},{"guess":"C","timestamp":73},{"blank":true},{},{},{},{},{},{"blank":true},{},{},{"timestamp":5440},{},{"guess":"S","timestamp":6},{"guess":"T","timestamp":77},{"guess":"O","timestamp":15},{"guess":"C","timestamp":38762},{"guess":"K","timestamp":126640896},{"guess":"E","timestamp":126640897},{"guess":"X","timestamp":126640897},{"guess":"C","timestamp":126640898},{"guess":"H","timestamp":126640898},{"guess":"A","timestamp":126640899},{"guess":"N","timestamp":126640899},{"guess":"G","timestamp":126640899},{"guess":"E","timestamp":126640899},{"guess":"S","timestamp":126640900},{"blank":true},{"blank":true},{"blank":true},{"blank":true},{"guess":"A","timestamp":38762},{},{},{},{},{},{},{"guess":"E","timestamp":126640918},{},{"blank":true},{"blank":true},{"blank":true},{"blank":true},{},{"guess":"W","timestamp":5308},{"guess":"I","timestamp":38762},{},{},{},{},{},{},{"guess":"T","timestamp":126640919},{},{"guess":"L","timestamp":126640988},{"guess":"E","timestamp":126640983},{"guess":"S","timestamp":126640978},{"guess":"C","timestamp":5312},{"guess":"O","timestamp":5311},{"guess":"E","timestamp":5305},{"guess":"N","timestamp":5311},{"blank":true},{},{},{},{},{},{"blank":true},{"guess":"D","timestamp":126640985},{"guess":"A","timestamp":126640985},{"guess":"N","timestamp":126640983},{"guess":"K","timestamp":126640979},{"guess":"A","timestamp":5293},{"guess":"N","timestamp":5294},{"guess":"T","timestamp":5294},{"blank":true},{"guess":"S","timestamp":126640957},{"guess":"T","timestamp":126640957},{"guess":"A","timestamp":126640957},{"guess":"T","timestamp":126640958},{"blank":true},{"blank":true},{"guess":"C","timestamp":5329},{"guess":"Y","timestamp":5329},{"guess":"N","timestamp":5329},{"guess":"D","timestamp":5330},{"guess":"I","timestamp":5330},{},{},{"guess":"S","timestamp":5306},{"guess":"E","timestamp":5528},{},{},{},{"blank":true},{"guess":"N","timestamp":5555},{"guess":"B","timestamp":5557},{"guess":"A","timestamp":5346},{"blank":true},{"guess":"C","timestamp":126640970},{"guess":"U","timestamp":126640970},{"guess":"R","timestamp":126640971},{},{},{"guess":"U","timestamp":5306},{"guess":"A","timestamp":5528},{},{"blank":true},{"guess":"P","timestamp":126640976},{"guess":"O","timestamp":70924},{"guess":"O","timestamp":70921},{"guess":"R","timestamp":70932},{"guess":"S","timestamp":5346},{"guess":"P","timestamp":70948},{"guess":"O","timestamp":126640977},{"guess":"R","timestamp":126640977},{"guess":"T","timestamp":126640980},{},{},{"guess":"I","timestamp":5307},{"guess":"V","timestamp":5532},{},{"blank":true},{"guess":"S","timestamp":70916},{"guess":"O","timestamp":70917},{"guess":"M","timestamp":70917},{"guess":"E","timestamp":70917},{"guess":"T","timestamp":5346},{"guess":"I","timestamp":70918},{"guess":"M","timestamp":70918},{"guess":"E","timestamp":70918},{"guess":"S","timestamp":70918},{},{},{"guess":"T","timestamp":5307},{"guess":"E","timestamp":5529},{},{"blank":true},{"blank":true},{"guess":"F","timestamp":70924},{"guess":"E","timestamp":70921},{"guess":"D","timestamp":70928},{"guess":"E","timestamp":5347},{"guess":"X","timestamp":70928},{"guess":"E","timestamp":70929},{"guess":"S","timestamp":70929},{"blank":true}]},"calcs":{"percentFilled":66,"secondsSpentSolving":1799},"firsts":{"opened":1428032399},"lastCommitID":"04ECE9","puzzleID":9877,"timestamp":1554673403,"userID":55348624,"minGuessTime":1428032413}