{"board":{"cells":[{"guess":"A","timestamp":1},{"guess":"S","timestamp":10},{"guess":"H","timestamp":12},{"blank":true},{"guess":"B","timestamp":52},{"guess":"B","timestamp":62},{"guess":"C","timestamp":61},{"blank":true},{"blank":true},{"guess":"S","timestamp":285},{"guess":"C","timestamp":189},{"guess":"R","timestamp":192},{"guess":"A","timestamp":276},{"guess":"W","timestamp":284},{"guess":"L","timestamp":284},{"guess":"T","timestamp":17},{"guess":"H","timestamp":10},{"guess":"E","timestamp":13},{"guess":"A","timestamp":71},{"guess":"T","timestamp":52},{"guess":"E","timestamp":179},{"guess":"A","timestamp":362},{"guess":"M","timestamp":346},{"blank":true},{"guess":"A","timestamp":8510},{"guess":"R","timestamp":8507},{"guess":"A","timestamp":192},{"guess":"B","timestamp":281},{"guess":"I","timestamp":8509},{"guess":"A","timestamp":8490},{"guess":"M","timestamp":24},{"guess":"E","timestamp":11},{"guess":"A","timestamp":13},{"guess":"C","timestamp":28},{"guess":"U","timestamp":28},{"guess":"L","timestamp":28},{"guess":"P","timestamp":28},{"guess":"A","timestamp":152},{"blank":true},{},{"guess":"A","timestamp":189},{"guess":"T","timestamp":70556},{"guess":"A","timestamp":70559},{"guess":"N","timestamp":8536},{"guess":"T","timestamp":8491},{"guess":"F","timestamp":88},{"guess":"E","timestamp":11},{"guess":"R","timestamp":13},{"guess":"N","timestamp":75},{"blank":true},{"guess":"G","timestamp":165},{"guess":"I","timestamp":165},{"guess":"R","timestamp":165},{"guess":"D","timestamp":166},{"blank":true},{"guess":"M","timestamp":188},{"guess":"A","timestamp":192},{"guess":"T","timestamp":196},{"guess":"T","timestamp":196},{"guess":"E","timestamp":197},{"guess":"E","timestamp":8559},{"guess":"S","timestamp":11},{"guess":"T","timestamp":14},{"guess":"E","timestamp":77},{"guess":"E","timestamp":8556},{"blank":true},{"guess":"T","timestamp":358},{"guess":"I","timestamp":347},{"guess":"E","timestamp":337},{"guess":"U","timestamp":359},{"guess":"P","timestamp":188},{"blank":true},{"guess":"T","timestamp":278},{"guess":"E","timestamp":8493},{"guess":"X","timestamp":8490},{},{"guess":"H","timestamp":11},{"guess":"S","timestamp":14},{"blank":true},{"guess":"K","timestamp":340},{"guess":"O","timestamp":341},{"guess":"A","timestamp":341},{"guess":"L","timestamp":341},{"guess":"A","timestamp":338},{"guess":"S","timestamp":333},{"blank":true},{"guess":"C","timestamp":252},{"guess":"O","timestamp":254},{"guess":"R","timestamp":255},{"guess":"E","timestamp":255},{"blank":true},{"blank":true},{"blank":true},{"guess":"D","timestamp":386},{"guess":"I","timestamp":272},{"guess":"L","timestamp":272},{"guess":"L","timestamp":272},{"guess":"Y","timestamp":272},{"guess":"D","timestamp":272},{"guess":"A","timestamp":273},{"guess":"L","timestamp":273},{"guess":"L","timestamp":252},{"guess":"I","timestamp":274},{"guess":"E","timestamp":262},{"guess":"S","timestamp":200},{"blank":true},{"guess":"S","timestamp":8213},{"guess":"O","timestamp":8213},{"guess":"U","timestamp":386},{"guess":"N","timestamp":8213},{"guess":"D","timestamp":374},{"guess":"I","timestamp":8214},{"guess":"N","timestamp":347},{"guess":"G","timestamp":8215},{"guess":"B","timestamp":360},{"guess":"O","timestamp":328},{"guess":"A","timestamp":252},{"guess":"R","timestamp":276},{"guess":"D","timestamp":262},{"blank":true},{"guess":"G","timestamp":11037},{"guess":"E","timestamp":8567},{"timestamp":70522},{"guess":"R","timestamp":386},{"guess":"G","timestamp":8238},{"guess":"E","timestamp":374},{},{"guess":"M","timestamp":347},{"guess":"I","timestamp":8217},{"guess":"L","timestamp":361},{"guess":"E","timestamp":8314},{"guess":"Y","timestamp":252},{"blank":true},{"blank":true},{"blank":true},{"guess":"I","timestamp":8271},{"guess":"T","timestamp":8271},{"guess":"S","timestamp":8273},{"guess":"A","timestamp":387},{"blank":true},{"guess":"S","timestamp":374},{},{"guess":"A","timestamp":8373},{"guess":"V","timestamp":70548},{"guess":"E","timestamp":361},{"guess":"S","timestamp":8315},{"blank":true},{"guess":"G","timestamp":8420},{"guess":"E","timestamp":8406},{"guess":"E","timestamp":8422},{"guess":"G","timestamp":11056},{"guess":"A","timestamp":8568},{"guess":"P","timestamp":11059},{"blank":true},{"guess":"S","timestamp":8378},{"guess":"T","timestamp":375},{"guess":"I","timestamp":8379},{"guess":"N","timestamp":8374},{"guess":"E","timestamp":8218},{"blank":true},{"guess":"S","timestamp":8315},{"guess":"T","timestamp":8395},{"guess":"E","timestamp":8419},{"guess":"A","timestamp":8406},{"guess":"M","timestamp":8425},{"guess":"A","timestamp":8327},{"guess":"S","timestamp":8327},{"guess":"O","timestamp":8329},{"guess":"N","timestamp":8330},{"guess":"E","timestamp":8331},{"blank":true},{},{"guess":"S","timestamp":8374},{"guess":"A","timestamp":70548},{},{"blank":true},{"guess":"O","timestamp":8351},{"guess":"N","timestamp":8352},{"guess":"T","timestamp":8353},{"guess":"O","timestamp":8353},{"guess":"T","timestamp":67502},{"guess":"I","timestamp":8568},{"timestamp":70526},{},{"guess":"N","timestamp":67473},{"guess":"A","timestamp":67483},{"blank":true},{"guess":"O","timestamp":8365},{"guess":"W","timestamp":8218},{"guess":"L","timestamp":8365},{"guess":"S","timestamp":8429},{"guess":"N","timestamp":8391},{"guess":"E","timestamp":8397},{"guess":"S","timestamp":8397},{"guess":"T","timestamp":8399},{"guess":"O","timestamp":67478},{"guess":"D","timestamp":8569},{"guess":"E","timestamp":67478},{"guess":"S","timestamp":67479},{"guess":"S","timestamp":67475},{"guess":"A","timestamp":67481},{"blank":true},{"guess":"N","timestamp":8375},{"guess":"A","timestamp":70549},{},{},{"guess":"E","timestamp":8394},{"guess":"V","timestamp":8419},{"guess":"I","timestamp":8407},{"guess":"E","timestamp":8426},{"guess":"N","timestamp":67463},{"guess":"E","timestamp":8569},{"guess":"S","timestamp":67463},{"guess":"T","timestamp":67464},{"guess":"E","timestamp":67464},{"guess":"A","timestamp":67464},{"blank":true},{"blank":true},{"guess":"Y","timestamp":70549},{"timestamp":67427},{},{"blank":true},{"guess":"A","timestamp":8420},{"guess":"N","timestamp":8407},{"guess":"D","timestamp":8426}]},"calcs":{"percentFilled":94,"secondsSpentSolving":1185},"firsts":{"opened":1493431303},"lastCommitID":"E7DB5E","puzzleID":13189,"timestamp":1493561641,"userID":55348624,"minGuessTime":1493431307}